tela/__init__.py
tela/_base_client.py
tela/_client.py
tela/_compat.py
tela/_constants.py
tela/_exceptions.py
tela/_files.py
tela/_legacy_response.py
tela/_models.py
tela/_qs.py
tela/_resource.py
tela/_response.py
tela/_streaming.py
tela/_types.py
tela/_utils/__init__.py
tela/_utils/_logs.py
tela/_utils/_proxy.py
tela/_utils/_reflection.py
tela/_utils/_streams.py
tela/_utils/_sync.py
tela/_utils/_transform.py
tela/_utils/_typing.py
tela/_utils/_utils.py
tela/_version.py
tela/resources/__init__.py
tela/resources/chat/__init__.py
tela/resources/chat/completions.py
tela/types/__init__.py
tela/types/chat/__init__.py
tela/types/chat/chat_completion.py
tela/types/chat/chat_completion_file.py
tela/types/chat/chat_completions_create_param.py
tela/version.py
tela-0.2.2.dist-info/METADATA
tela-0.2.2.dist-info/WHEEL
tela-0.2.2.dist-info/RECORD
