Metadata-Version: 2.1
Name: tela
Version: 0.2.2
Summary: The official Python library for the Tela API
Author: Thierry
Author-email: thierry@tela.com
Requires-Python: >=3.10,<4.0
Classifier: Programming Language :: Python :: 3
Classifier: Programming Language :: Python :: 3.10
Classifier: Programming Language :: Python :: 3.11
Classifier: Programming Language :: Python :: 3.12
Classifier: Programming Language :: Python :: 3.13
Requires-Dist: anyio (>=4.6.0,<5.0.0)
Requires-Dist: distro (>=1.9.0,<2.0.0)
Requires-Dist: httpx (>=0.27.2,<0.28.0)
Requires-Dist: pydantic (>=2.9.2,<3.0.0)
